hypermodern_python_tuto/__init__.py
hypermodern_python_tuto/__main__.py
hypermodern_python_tuto/ui.py
hypermodern_python_tuto/wikipedia/article.py
hypermodern_python_tuto/wikipedia/article_schema.py
hypermodern_python_tuto/wikipedia/language.py
hypermodern_python_tuto/wikipedia/requester.py
hypermodern_python_tuto-1.0.4.dist-info/LICENSE
hypermodern_python_tuto-1.0.4.dist-info/WHEEL
hypermodern_python_tuto-1.0.4.dist-info/entry_points.txt
hypermodern_python_tuto-1.0.4.dist-info/METADATA
hypermodern_python_tuto-1.0.4.dist-info/RECORD
