Metadata-Version: 2.1
Name: hypermodern-python-tuto
Version: 1.0.4
Summary: Repo to follow the Claudio Jolowicz's tutorial about Hypermodern Python (https://cjolowicz.github.io/posts/hypermodern-python-01-setup/)
Home-page: https://github.com/le-chartreux/hypermodern-python-tuto
License: MIT
Keywords: hypermodern
Author: le-chartreux
Author-email: le-chartreux-vert@protonmail.com
Requires-Python: >=3.10,<4.0
Classifier: License :: OSI Approved :: MIT License
Classifier: Programming Language :: Python :: 3
Classifier: Programming Language :: Python :: 3.10
Classifier: Programming Language :: Python :: 3.11
Requires-Dist: click (>=8.1.3,<9.0.0)
Requires-Dist: marshmallow (>=3.19.0,<4.0.0)
Requires-Dist: requests (>=2.28.2,<3.0.0)
Project-URL: Documentation, https://hypermodern-python-tuto.readthedocs.io
Project-URL: Repository, https://github.com/le-chartreux/hypermodern-python-tuto
